libmercury/__init__.py
libmercury/__main__.py
libmercury/route_management.py
libmercury/utils.py
libmercury/version.py
libmercury/wizard.py
libmercury/wsgi.py
libmercury/__pycache__/Validator.cpython-310.pyc
libmercury/__pycache__/__init__.cpython-310.pyc
libmercury/__pycache__/__init__.cpython-312.pyc
libmercury/__pycache__/__init__.cpython-314.pyc
libmercury/__pycache__/__main__.cpython-310.pyc
libmercury/__pycache__/__main__.cpython-312.pyc
libmercury/__pycache__/route_management.cpython-310.pyc
libmercury/__pycache__/route_management.cpython-312.pyc
libmercury/__pycache__/utils.cpython-310.pyc
libmercury/__pycache__/utils.cpython-312.pyc
libmercury/__pycache__/version.cpython-310.pyc
libmercury/__pycache__/version.cpython-312.pyc
libmercury/__pycache__/wizard.cpython-310.pyc
libmercury/__pycache__/wizard.cpython-312.pyc
libmercury/__pycache__/wsgi.cpython-310.pyc
libmercury/__pycache__/wsgi.cpython-312.pyc
libmercury/db/MigrationGenerator.py
libmercury/db/__init__.py
libmercury/db/connection.py
libmercury/db/setup_db.py
libmercury/db/__pycache__/MigrationGenerator.cpython-310.pyc
libmercury/db/__pycache__/MigrationGenerator.cpython-312.pyc
libmercury/db/__pycache__/__init__.cpython-310.pyc
libmercury/db/__pycache__/__init__.cpython-312.pyc
libmercury/db/__pycache__/connection.cpython-310.pyc
libmercury/db/__pycache__/connection.cpython-312.pyc
libmercury/db/__pycache__/setup_db.cpython-310.pyc
libmercury/db/__pycache__/setup_db.cpython-312.pyc
libmercury/generation/__init__.py
libmercury/generation/generator.py
libmercury/generation/__pycache__/__init__.cpython-310.pyc
libmercury/generation/__pycache__/__init__.cpython-312.pyc
libmercury/generation/__pycache__/generator.cpython-310.pyc
libmercury/generation/__pycache__/generator.cpython-312.pyc
libmercury/security/__init__.py
libmercury/security/hashing.py
libmercury/security/jwt.py
libmercury/security/keygen.py
libmercury/security/__pycache__/__init__.cpython-310.pyc
libmercury-0.85.dist-info/LICENSE
libmercury-0.85.dist-info/METADATA
libmercury-0.85.dist-info/WHEEL
libmercury-0.85.dist-info/top_level.txt
libmercury-0.85.dist-info/RECORD
